imhotep_files_flask/__init__.py
imhotep_files_flask/main.py
imhotep_files_flask-0.1.dist-info/METADATA
imhotep_files_flask-0.1.dist-info/WHEEL
imhotep_files_flask-0.1.dist-info/entry_points.txt
imhotep_files_flask-0.1.dist-info/top_level.txt
imhotep_files_flask-0.1.dist-info/RECORD
