Metadata-Version: 2.1
Name: imhotep_files_flask
Version: 0.1
Summary: A Flask library for secure file uploads and deletions
Home-page: https://github.com/Imhotep-Tech/imhotep_files_flask
Author: Karim Bassem
Author-email: imhoteptech@outlook.com
Classifier: Programming Language :: Python :: 3
Classifier: License :: OSI Approved :: MIT License
Classifier: Operating System :: OS Independent
Requires-Python: >=3.6
Requires-Dist: Flask
Requires-Dist: Werkzeug
